paperpilot_common/__init__.py
paperpilot_common/auth/__init__.py
paperpilot_common/auth/authentications.py
paperpilot_common/auth/backends.py
paperpilot_common/auth/exceptions.py
paperpilot_common/auth/serializers.py
paperpilot_common/auth/views.py
paperpilot_common/exceptions/__init__.py
paperpilot_common/exceptions/configs.py
paperpilot_common/exceptions/handler.py
paperpilot_common/exceptions/types.py
paperpilot_common/exceptions/views.py
paperpilot_common/grpc/__init__.py
paperpilot_common/grpc/apps.py
paperpilot_common/grpc/client/__init__.py
paperpilot_common/grpc/client/cache.py
paperpilot_common/grpc/client/client.py
paperpilot_common/grpc/client/wrapper.py
paperpilot_common/grpc/config.py
paperpilot_common/grpc/context.py
paperpilot_common/grpc/helpers/__init__.py
paperpilot_common/grpc/helpers/ratelimit.py
paperpilot_common/grpc/management/__init__.py
paperpilot_common/grpc/management/commands/grpcserver.py
paperpilot_common/grpc/models.py
paperpilot_common/grpc/serializers/__init__.py
paperpilot_common/grpc/serializers/base.py
paperpilot_common/grpc/signals/__init__.py
paperpilot_common/grpc/signals/wrapper.py
paperpilot_common/grpc/utils.py
paperpilot_common/helper/__init__.py
paperpilot_common/helper/context.py
paperpilot_common/helper/field.py
paperpilot_common/helper/grpc_wrapper.py
paperpilot_common/logs/__init__.py
paperpilot_common/logs/admin.py
paperpilot_common/logs/apps.py
paperpilot_common/logs/configs.py
paperpilot_common/logs/handler.py
paperpilot_common/logs/middleware.py
paperpilot_common/logs/migrations/0001_initial.py
paperpilot_common/logs/migrations/0002_alter_requestlog_content_type_and_more.py
paperpilot_common/logs/migrations/__init__.py
paperpilot_common/logs/models.py
paperpilot_common/logs/templates/change_form.html
paperpilot_common/logs/templates/charts_change_list.html
paperpilot_common/logs/threads.py
paperpilot_common/logs/types.py
paperpilot_common/logs/utils.py
paperpilot_common/meili/__init__.py
paperpilot_common-0.3.2.dist-info/METADATA
paperpilot_common-0.3.2.dist-info/WHEEL
paperpilot_common-0.3.2.dist-info/RECORD
