Metadata-Version: 2.1
Name: paperpilot-common
Version: 0.3.2
Summary: PaperPilot 公共包及接口定义
Home-page: https://github.com/Nagico/paperpilot-common
Author: Nagico
Author-email: coyangjr@whu.edu.cn
Requires-Python: >=3.10,<4.0
Classifier: Programming Language :: Python :: 3
Classifier: Programming Language :: Python :: 3.10
Classifier: Programming Language :: Python :: 3.11
Classifier: Programming Language :: Python :: 3.12
Requires-Dist: googleapis-common-protos (>=1.56.3)
Requires-Dist: grpc-stubs (>=1.53.0)
Requires-Dist: grpcio (>=1.58.0)
Requires-Dist: grpcio-health-checking (>=1.59.0,<2.0.0)
Requires-Dist: grpcio-reflection (>=1.59.0)
Requires-Dist: grpcio-status (>=1.58.0)
Requires-Dist: grpcio-tools (>=1.58.0)
Requires-Dist: isodate (>=0.6.1)
Requires-Dist: loguru (>=0.7.2)
Project-URL: Repository, https://github.com/Nagico/paperpilot-common
